<?xml version="1.0" encoding="UTF-8" standalone="yes"?>





<item>
<title>[COLOR yellow] _**_  [/COLOR][COLOR  skyblue] TEMPORADA 1 CAP 1 [/COLOR][COLOR yellow]  _**_ [/COLOR]</title>
<urlsolve>http://streamcloud.eu/jpmjjf427l6j</urlsolve>
<thumbnail>http://www.seriespapaya.com/uploads/Hostages-(Rehenes)35.jpg<thumbnail>
<info></info> 
</item>

<item>
<title>[COLOR yellow] _**_  [/COLOR][COLOR  skyblue] TEMPORADA 1 CAP 2 [/COLOR][COLOR yellow]  _**_ [/COLOR]</title>
<urlsolve>http://streamcloud.eu/urpt4bdjia5o</urlsolve>
<thumbnail>http://www.seriespapaya.com/uploads/Hostages-(Rehenes)35.jpg<thumbnail>
<info></info> 
</item>


<item>
<title>[COLOR yellow] _**_  [/COLOR][COLOR  skyblue] TEMPORADA 1 CAP 3 [/COLOR][COLOR yellow]  _**_ [/COLOR]</title>
<urlsolve>http://streamcloud.eu/tdulf37s40x4</urlsolve>
<thumbnail>http://www.seriespapaya.com/uploads/Hostages-(Rehenes)35.jpg<thumbnail>
<info></info> 
</item>


<item>
<title>[COLOR yellow] _**_  [/COLOR][COLOR  skyblue] TEMPORADA 1 CAP 4 [/COLOR][COLOR yellow]  _**_ [/COLOR]</title>
<urlsolve>http://streamcloud.eu/g3aft53tfzmg</urlsolve>
<thumbnail>http://www.seriespapaya.com/uploads/Hostages-(Rehenes)35.jpg<thumbnail>
<info></info> 
</item>

<item>
<title>[COLOR yellow] _**_  [/COLOR][COLOR  skyblue] TEMPORADA 1 CAP 5 [/COLOR][COLOR yellow]  _**_ [/COLOR]</title>
<urlsolve>http://streamcloud.eu/ns6rf1oa332z</urlsolve>
<thumbnail>http://www.seriespapaya.com/uploads/Hostages-(Rehenes)35.jpg<thumbnail>
<info></info> 
</item>

<item>
<title>[COLOR yellow] _**_  [/COLOR][COLOR  skyblue] TEMPORADA 1 CAP 6 [/COLOR][COLOR yellow]  _**_ [/COLOR]</title>
<urlsolve>http://streamcloud.eu/ebjp0w25jj6o</urlsolve>
<thumbnail>http://www.seriespapaya.com/uploads/Hostages-(Rehenes)35.jpg<thumbnail>
<info></info> 
</item>


<item>
<title>[COLOR yellow] _**_  [/COLOR][COLOR  skyblue] TEMPORADA 1 CAP 7 [/COLOR][COLOR yellow]  _**_ [/COLOR]</title>
<urlsolve>http://streamcloud.eu/lqvoc24ai89n</urlsolve>
<thumbnail>http://www.seriespapaya.com/uploads/Hostages-(Rehenes)35.jpg<thumbnail>
<info></info> 
</item>


<item>
<title>[COLOR yellow] _**_  [/COLOR][COLOR  skyblue] TEMPORADA 1 CAP 8 [/COLOR][COLOR yellow]  _**_ [/COLOR]</title>
<urlsolve>http://streamcloud.eu/g2f78mzqunmo</urlsolve>
<thumbnail>http://www.seriespapaya.com/uploads/Hostages-(Rehenes)35.jpg<thumbnail>
<info></info> 
</item>

<item>
<title>[COLOR yellow] _**_  [/COLOR][COLOR  skyblue] TEMPORADA 1 CAP 9 [/COLOR][COLOR yellow]  _**_ [/COLOR]</title>
<urlsolve>http://streamcloud.eu/5mpujnkq2k7u</urlsolve>
<thumbnail>http://www.seriespapaya.com/uploads/Hostages-(Rehenes)35.jpg<thumbnail>
<info></info> 
</item>

<item>
<title>[COLOR yellow] _**_  [/COLOR][COLOR  skyblue] TEMPORADA 1 CAP 10 [/COLOR][COLOR yellow]  _**_ [/COLOR]</title>
<urlsolve>http://streamcloud.eu/85sxw8v1oo3r</urlsolve>
<thumbnail>http://www.seriespapaya.com/uploads/Hostages-(Rehenes)35.jpg<thumbnail>
<info></info> 
</item>

<item>
<title>[COLOR yellow] _**_  [/COLOR][COLOR  skyblue] TEMPORADA 1 CAP 11 [/COLOR][COLOR yellow]  _**_ [/COLOR]</title>
<urlsolve>http://streamcloud.eu/v42eky0m1q0c</urlsolve>
<thumbnail>http://www.seriespapaya.com/uploads/Hostages-(Rehenes)35.jpg<thumbnail>
<info></info> 
</item>

<item>
<title>[COLOR yellow] _**_  [/COLOR][COLOR  skyblue] TEMPORADA 1 CAP 12 [/COLOR][COLOR yellow]  _**_ [/COLOR]</title>
<urlsolve>http://streamcloud.eu/ejtj81zlgexr</urlsolve>
<thumbnail>http://www.seriespapaya.com/uploads/Hostages-(Rehenes)35.jpg<thumbnail>
<info></info> 
</item>

<item>
<title>[COLOR yellow] _**_  [/COLOR][COLOR  skyblue] TEMPORADA 1 CAP 13 [/COLOR][COLOR yellow]  _**_ [/COLOR]</title>
<urlsolve>http://streamcloud.eu/ff65qjlmdvm6</urlsolve>
<thumbnail>http://www.seriespapaya.com/uploads/Hostages-(Rehenes)35.jpg<thumbnail>
<info></info> 
</item>


<item>
<title>[COLOR yellow] _**_  [/COLOR][COLOR  skyblue] TEMPORADA 1 CAP 14 [/COLOR][COLOR yellow]  _**_ [/COLOR]</title>
<urlsolve>http://streamcloud.eu/h80xluq60b1l</urlsolve>
<thumbnail>http://www.seriespapaya.com/uploads/Hostages-(Rehenes)35.jpg<thumbnail>
<info></info> 
</item>

<item>
<title>[COLOR yellow] _**_  [/COLOR][COLOR  skyblue] TEMPORADA 1 CAP 15 [/COLOR][COLOR yellow]  _**_ [/COLOR]</title>
<urlsolve>http://streamcloud.eu/9ayj97yusiji</urlsolve>
<thumbnail>http://www.seriespapaya.com/uploads/Hostages-(Rehenes)35.jpg<thumbnail>
<info></info> 
</item>
